[
  {
    "title": "",
    "data": ""
  },
  {
    "title": "",
    "data": ""
  },
  {
    "title": "中医简介",
    "data": [
      {
        "title": "整体观念",
        "content": "中医看待人体为一个有机整体，强调身体、心理和社会环境的相互关联。"
      },
      {
        "title": "阴阳五行",
        "content": "中医理论基于阴阳和五行理论，通过平衡阴阳和五行来维护身体健康。"
      },
      {
        "title": "气血理论",
        "content": "气和血是中医理论中的关键概念，与健康密切相关。"
      },
      {
        "title": "诊断方法",
        "content": "中医使用一系列诊断方法，包括望、闻、问、切，以帮助诊断疾病。"
      },
      {
        "title": "中药治疗",
        "content": "中医使用天然草本药物作为治疗的一部分，药方根据患者症状和体质而定。"
      },
      {
        "title": "针灸疗法",
        "content": "针灸是中医的一种疗法，通过在特定穴位上插入针来调整气血流动和能量。"
      },
      {
        "title": "饮食疗法",
        "content": "中医饮食理论强调根据体质和季节来调整饮食，以维持身体的平衡。"
      },
      {
        "title": "预防为主",
        "content": "中医强调预防疾病胜于治疗，提倡健康的生活方式和饮食习惯。"
      },
      {
        "title": "个性化治疗",
        "content": "中医治疗是高度个性化的，根据患者的病情、体质和生活环境制定治疗方案。"
      }
    ]
  },
  {
    "title": "中医养生",
    "data": [

        {
          "title": "饮食调养",
          "content": "中医饮食理论强调根据个体的体质、季节和疾病倾向来调整饮食，以维持身体的平衡。"
        },
        {
          "title": "运动锻炼",
          "content": "中医认为适度的运动可以促进气血流通，增强体质，提高免疫力。"
        },
        {
          "title": "针灸和中药",
          "content": "针灸是一种中医疗法，通过在特定穴位上插入针来促进身体的能量流动。中药是一种天然草药的药物疗法，用于调理身体和治疗疾病。"
        },
        {
          "title": "中医按摩",
          "content": "中医按摩技术，如推拿和拔罐，可以帮助舒缓肌肉疼痛，促进血液循环，减轻压力和焦虑。"
        },
        {
          "title": "足疗",
          "content": "中医足疗利用足部的反射区来刺激身体各个器官和系统，以促进健康和缓解症状。"
        },
        {
          "title": "精神调理",
          "content": "中医强调情绪和思维对健康的影响，维持情绪的平衡和正面思维对整体健康至关重要。"
        },
        {
          "title": "中医养生",
          "content": "中医养生包括遵循生活节律、保持适度的休息和睡眠、保持适度的体重、避免过度疲劳和消耗精力、保持适度的湿度和温度环境等。"
        },
        {
          "title": "中医季节保健",
          "content": "中医认为季节对身体有影响，因此建议在不同的季节采取不同的保健措施，如调整饮食和生活方式。"
        },
        {
          "title": "预防为主",
          "content": "中医强调预防疾病胜于治疗。通过调整生活方式、饮食和心态，可以预防许多慢性疾病和健康问题。"
        }
      ]
  },
  {
    "title": "中医治疗",
    "data": [
      {
        "title": "高血压",
        "content": "高血压患者应该控制饮食，减少高盐食物和高脂食物的摄入，适度运动，保持适当体重，减轻压力，定期监测血压。"
      },
      {
        "title": "糖尿病",
        "content": "糖尿病患者需要严格控制饮食，控制碳水化合物摄入，定期监测血糖，适度运动，按医嘱服药，避免情绪波动。"
      },
      {
        "title": "心脏病",
        "content": "心脏病患者应遵循低脂、低盐饮食，戒烟限酒，定期锻炼，控制体重，按医嘱服药，减轻压力，保持规律的生活作息。"
      },
      {
        "title": "慢性疼痛",
        "content": "慢性疼痛患者可以通过定期运动、保持适当体重，减轻负重，练习放松技巧，保持积极的心态来缓解疼痛。"
      },
      {
        "title": "哮喘",
        "content": "哮喘患者需要避免接触过敏原，定期服用维持药物，保持干燥和洁净的居住环境，避免剧烈运动，控制情绪，遵循医嘱。"
      }
    ]

  },
  {"title": "西医治疗",
    "data":[
      {
        "title": "心绞痛",
        "content": "心绞痛是一种急性心血管事件，可能表现为胸痛、呼吸困难、恶心等症状。患者应立即就医，接受心电图检查和相关治疗。"
      },
      {
        "title": "中风",
        "content": "中风是急性脑血管事件，可能导致瘫痪、言语障碍等症状。患者应立刻就医，以争取最佳的治疗机会。"
      },
      {
        "title": "心肌梗塞",
        "content": "心肌梗塞是急性心血管事件，表现为剧烈的胸痛、出冷汗、呼吸急促等症状。患者应紧急就医，接受急救和冠状动脉介入治疗。"
      },
      {
        "title": "严重呼吸窘迫",
        "content": "严重呼吸窘迫可能是由各种原因引起的急性呼吸道疾病，如哮喘恶化或肺部感染。患者应立即就医，可能需要氧气治疗和药物干预。"
      },
      {
        "title": "重度外伤",
        "content": "严重外伤如重型交通事故、跌落等可能导致骨折、内出血等情况。患者应立即就医，接受紧急救护和手术治疗。"
      }
    ]
  },
  {"title": "西医用药",
    "data": [
      {
        "title": "感冒",
        "content": "感冒是一种常见的病毒性感染，常表现为喉咙痛、流感症状和发热。通常可以通过休息和非处方药物缓解症状，如退热药和感冒药。"
      },
      {
        "title": "发热",
        "content": "发热可能是许多疾病的症状，包括感染和炎症。医生可能会开具退热药或抗生素，根据具体情况治疗。"
      },
      {
        "title": "头痛",
        "content": "头痛可能由多种原因引起，包括偏头痛、紧张性头痛等。非处方药物如布洛芬或阿司匹林可以帮助缓解头痛。"
      },
      {
        "title": "过敏",
        "content": "过敏反应可能表现为皮肤瘙痒、鼻塞、打喷嚏等症状。抗过敏药物如抗组胺药可以缓解过敏症状。"
      },
      {
        "title": "胃炎",
        "content": "胃炎是胃黏膜炎症，通常由细菌感染或饮食不当引起。医生可能会开具抗生素或胃药来治疗胃炎。"
      }
    ]

  },
  {
    "title": "西医科普",
    "data":
    [
      {
        "title": "西医简介",
        "content": "西医学是一门医学体系，源自古希腊和罗马，强调基于科学研究和证据的医疗实践。西医学通常使用生化、解剖学和药理学等科学原理来诊断和治疗疾病。"
      },
      {
        "title": "西医诊断",
        "content": "西医诊断依赖于症状、体格检查和医学检查。医生通常使用X射线、血液检查、MRI和CT扫描等工具来帮助确诊疾病。"
      },
      {
        "title": "西医治疗方法",
        "content": "西医治疗方法包括药物治疗、手术、放射疗法、物理疗法等。药物治疗通常使用合成药物来干预生物化学过程。手术可以用于切除肿瘤、修复受伤组织等。"
      },
      {
        "title": "西医专科",
        "content": "西医学包括多个专科领域，如内科、外科、儿科、妇产科、神经科学、皮肤科等。每个专科都有其专门领域的医生。"
      },
      {
        "title": "西医研究与发展",
        "content": "西医学领域不断发展，科学研究和医疗技术的进步推动了医学的不断进步。西医学不仅治疗疾病，还研究疾病的发病机制和预防方法。"
      }
    ]

  },
  {
    "title": "运动种类",
    "data": [
      {
        "title": "散步",
        "content": "散步是中老年人常见的有氧运动，每天建议进行30分钟到1小时的散步。您可以选择在早晨或傍晚进行，以避免炎热的时段。适度的散步有助于改善心肺功能和关节灵活性，还能提高心情。"
      },
      {
        "title": "太极拳",
        "content": "太极拳是一种低强度的运动，每周至少练习3次，每次30分钟到1小时。它注重平衡、柔韧性和调整呼吸，有助于提高身体协调性和减轻压力。"
      },
      {
        "title": "瑜伽",
        "content": "瑜伽是一种综合性的身体和心灵锻炼，每周至少练习3次，每次45分钟到1小时。瑜伽可以增强肌肉、提高柔韧性，同时帮助放松身心。"
      },
      {
        "title": "游泳",
        "content": "游泳是一项全身性的运动，每周至少游泳2-3次，每次30分钟到1小时。它对关节友好，有助于提高心肺功能和肌肉力量。"
      },
      {
        "title": "自行车骑行",
        "content": "自行车骑行是一种有氧运动，每周至少骑行2-3次，每次30分钟到1小时。它可以提高心肺健康，同时是一种有趣的户外活动。"
      }
    ]

  },
  {
    "title": "运动前后",
    "data": [
      {
        "title": "散步",
        "content": "在开始散步前，请穿合适的鞋子，做5-10分钟的热身活动，如摆动手臂和慢慢走动。散步后，进行适度的伸展，以防止肌肉疲劳和酸痛。保持正确的姿势，避免剧烈动作。"
      },
      {
        "title": "太极拳",
        "content": "在开始太极拳前，请穿宽松的服装，放松身体，进行深呼吸和冥想，以帮助专注。练习结束后，进行缓慢的呼吸和冥想，有助于身体和心灵的放松。"
      },
      {
        "title": "瑜伽",
        "content": "在开始瑜伽前，请穿着舒适的服装，进行深呼吸和冥想，以平静心情。瑜伽结束后，进行深度伸展，有助于肌肉放松和柔韧性提高。"
      },
      {
        "title": "游泳",
        "content": "在开始游泳前，请确保水温适宜，进行热身游泳或浮动，适应水的感觉。游泳后，进行适度的深呼吸和伸展，以减轻肌肉疲劳。"
      },
      {
        "title": "自行车骑行",
        "content": "在开始自行车骑行前，请穿着舒适的服装，进行慢速骑行预热，适应骑行。骑行结束后，进行适度的伸展和深呼吸，以提高身体的柔韧性和放松。"
      }
    ]

  },
  { "title": "运动好处",
    "data": [
      {
        "title": "身体上的好处",
        "content": "运动有助于老年人保持健康的体重，增强肌肉和骨骼，提高灵活性和协调性。它还可以改善心血管健康，降低患心脏病和高血压的风险。此外，运动有助于增强免疫系统，减少患慢性疾病的风险，如糖尿病和骨质疏松症。"

      },
      {
        "title": "心理上的好处",
        "content": "运动对心理健康也有积极影响。它可以减轻焦虑和抑郁症状，提高情绪状态，促进良好的睡眠。运动还有助于增强自尊心和自信心，提高社交互动和社交支持，减轻孤独感。"
      },
      {
        "title": "整体健康的好处",
        "content": "除了身体和心理方面的好处，运动还有助于改善老年人的整体健康。它可以提高认知功能和大脑健康，减缓认知衰退的速度。运动还有助于管理慢性疾病，提高生活质量，延长寿命，使老年生活更加充实和活力四溢。"
      }
    ]

  },
  {
    "title": "失眠",
    "data":[
      {
        "title": "维护规律的作息时间",
        "content": "老年人应尽量每天保持相同的睡觉和醒来时间，以帮助身体建立健康的睡眠习惯。规律的作息可以调整生物钟，提高入睡和醒来的效率。"
      },
      {
        "title": "创建舒适的睡眠环境",
        "content": "确保卧室安静、舒适，床铺和枕头合适。调节室温和湿度，消除噪音和光线，以创造宜人的睡眠环境。"
      },
      {
        "title": "限制白天睡眠",
        "content": "老年人应尽量避免白天过长的睡眠，以免影响晚上的入睡。如果需要午睡，尽量将午睡时间控制在20-30分钟内，避免过长的白天睡眠。"
      },
      {
        "title": "避免刺激物质",
        "content": "减少咖啡因和酒精的摄入，尤其是在晚上。咖啡因和酒精可以干扰睡眠，应在晚餐后数小时内避免摄入。"
      },
      {
        "title": "药物治疗",
        "content": "在医生的建议下，老年人可以考虑使用药物来帮助入睡，但要注意潜在的副作用和依赖性。药物治疗应该是最后的选择，仅在其他方法无效时考虑使用。"
      }
    ]

  },
  {
    "title": "嗜睡",
    "data": [
      {
        "title": "规律作息",
        "content": " 规律作息时间：每天保持相同的睡觉和醒来时间，帮助调整生物钟，减少白天嗜睡的倾向。\n\n"
      },
      {
        "title": "适度的体育锻炼",
        "content": " 适度的体育锻炼：进行适度的身体活动，如散步、游泳或瑜伽，有助于提高体能，减少嗜睡的感觉。\n\n"
      },
      {
        "title": "均衡饮食",
        "content": " 均衡饮食：确保饮食均衡，包含蔬菜、水果、全麦食物和蛋白质，避免过度进食或摄入大量高糖食物，以维持血糖水平稳定。\n\n"
      },
      {
        "title": "减少咖啡因和糖分",
        "content": " 减少咖啡因和糖分摄入：避免过多的咖啡因和高糖饮料，尤其是在下午和晚上，以减少嗜睡的倾向。\n\n"
      },
      {
        "title": "充足的睡眠",
        "content": " 充足的夜间睡眠：确保晚上获得足够的睡眠，成年人通常需要7-9小时的睡眠，以减少白天的嗜睡感。"
      }
    ]

  },
  {
    "title": "易醒",
    "data": [
      {
        "title": "1. 生理变化",
        "content": "随着年龄的增长，老年人的生物钟可能发生改变，导致更早醒来。他们的睡眠质量可能下降，容易在凌晨醒来并难以再次入睡。"
      },
      {
        "title": "2. 尿频",
        "content": "老年人可能因尿频问题而容易醒来。尿频可能与年龄相关的尿道肌肉失去弹性、前列腺问题或其他健康问题有关。"
      },
      {
        "title": "3. 疼痛或不适",
        "content": "身体的疼痛或不适，如关节炎、背部疼痛或其他疾病，可能导致老年人在夜间醒来。疼痛会干扰睡眠，使他们难以保持连续的深度睡眠。"
      },
      {
        "title": "4. 药物副作用",
        "content": "一些老年人可能因使用特定药物而容易醒来，因为药物可能引起嗜睡感或导致睡眠中断。药物副作用可能会影响睡眠质量。"
      },
      {
        "title": "5. 心理压力和焦虑",
        "content": "心理压力、焦虑、抑郁或其他情绪问题可能导致老年人在夜间醒来。心理健康问题可以干扰正常的睡眠模式。"
      }
    ]


  },
  {"title": "饮食",
    "data":[
      {
        "title": "早餐",
        "content": "早餐应包括以下食物：\n\n- 高纤维麦片或燕麦片：有助于维持健康的胃肠功能。\n- 低脂牛奶或豆浆：提供钙质，有助于骨骼健康。\n- 新鲜水果，如苹果或香蕉：富含维生素和纤维，有助于维持免疫系统和消化健康。\n- 全麦面包或全麦饼干：提供复杂碳水化合物，有助于提供持久的能量。\n\n时间：早上7点至8点之间。\n\n好处：早餐提供身体所需的能量和营养，帮助提高警觉性和注意力。\n\n忌吃：避免过多的油炸食物，高糖食物和咖啡因，以避免胃部不适和血糖波动。"
      },
      {
        "title": "午餐",
        "content": "午餐应包括以下食物：\n\n- 瘦肉，如鸡胸肉或鱼：提供优质蛋白质和必需的氨基酸。\n- 多种蔬菜，如胡萝卜、西兰花和菠菜：富含维生素和纤维，有助于维持免疫系统和消化健康。\n- 糙米或全麦面食：提供复杂碳水化合物，有助于维持稳定的血糖水平。\n- 清淡的汤：提供额外的水分和养分。\n\n时间：中午12点至1点之间。\n\n好处：午餐提供了长时间的饱腹感和能量，有助于保持体力和精神状态。\n\n忌吃：避免过多的盐和高脂肪食物，以维护心血管健康。"
      },
      {
        "title": "晚餐",
        "content": "晚餐应包括以下食物：\n\n- 鱼或豆腐：提供优质蛋白质和必需的脂肪。\n- 多种绿叶蔬菜，如菜心、青菜和芥兰：富含维生素和矿物质，有助于维护健康。\n- 少量的全麦面食：提供复杂碳水化合物，有助于晚上的能量供应。\n- 低脂酸奶或豆浆：提供额外的蛋白质和钙质。\n\n时间：晚上6点至7点之间。\n\n好处：晚餐提供了晚上所需的营养，但是要保持轻盈，以避免晚上不适感和消化不良。\n\n忌吃：避免晚上过多的大餐，油腻食物和辛辣食物，以避免影响睡眠和胃部不适。"
      }
    ]

  }
]